jupad/__init__.py
jupad/__main__.py
jupad/_version.py
jupad/resources/icon.svg
jupad/tests/test_jupad.py
jupad-0.0.4.dist-info/LICENSE
jupad-0.0.4.dist-info/METADATA
jupad-0.0.4.dist-info/WHEEL
jupad-0.0.4.dist-info/entry_points.txt
jupad-0.0.4.dist-info/top_level.txt
jupad-0.0.4.dist-info/RECORD
