Metadata-Version: 2.2
Name: jupad
Version: 0.0.4
Summary: Python Notepad
Author-email: Idan Pazi <idan.kp@gmail.com>
License: Copyright (c) 2024 Idan Pazi
Project-URL: Homepage, https://github.com/idanpa/jupad
Project-URL: Bug Reports, https://github.com/idanpa/jupad/issues
Project-URL: Source, https://github.com/idanpa/jupad
Keywords: development
Classifier: License :: OSI Approved :: MIT License
Classifier: Programming Language :: Python :: 3
Classifier: Operating System :: OS Independent
Requires-Python: >=3.7
License-File: LICENSE
Requires-Dist: ipython
Requires-Dist: qtconsole
Requires-Dist: PyQt6
Requires-Dist: ansi2html
